RequestsHttpForHumans/README.md
RequestsHttpForHumans/__init__.py
RequestsHttpForHumans/__main__.py
RequestsHttpForHumans/file.epub
RequestsHttpForHumans/index.html
RequestsHttpForHumans/css/__init__.py
RequestsHttpForHumans/css/annotations.css
RequestsHttpForHumans/css/main.css
RequestsHttpForHumans/css/normalize.css
RequestsHttpForHumans/css/popup.css
RequestsHttpForHumans/font/__init__.py
RequestsHttpForHumans/font/fontello.eot
RequestsHttpForHumans/font/fontello.svg
RequestsHttpForHumans/font/fontello.ttf
RequestsHttpForHumans/font/fontello.woff
RequestsHttpForHumans/img/__init__.py
RequestsHttpForHumans/img/annotator-glyph-sprite.png
RequestsHttpForHumans/img/annotator-icon-sprite.png
RequestsHttpForHumans/img/apple-touch-icon.png
RequestsHttpForHumans/img/cancelfullscreen.png
RequestsHttpForHumans/img/close.png
RequestsHttpForHumans/img/fullscreen.png
RequestsHttpForHumans/img/loader.gif
RequestsHttpForHumans/img/menu-icon.png
RequestsHttpForHumans/img/save.png
RequestsHttpForHumans/img/saved.png
RequestsHttpForHumans/img/settings-s.png
RequestsHttpForHumans/img/settings.png
RequestsHttpForHumans/img/star.png
RequestsHttpForHumans/js/__init__.py
RequestsHttpForHumans/js/epub.js
RequestsHttpForHumans/js/epub.min.js
RequestsHttpForHumans/js/epub.min.map
RequestsHttpForHumans/js/hooks.min.js
RequestsHttpForHumans/js/hooks.min.map
RequestsHttpForHumans/js/reader.js
RequestsHttpForHumans/js/reader.js.map
RequestsHttpForHumans/js/reader.min.js
RequestsHttpForHumans/js/reader.min.map
RequestsHttpForHumans/js/hooks/__init__.py
RequestsHttpForHumans/js/hooks/extensions/__init__.py
RequestsHttpForHumans/js/hooks/extensions/highlight.js
RequestsHttpForHumans/js/libs/__init__.py
RequestsHttpForHumans/js/libs/jquery.min.js
RequestsHttpForHumans/js/libs/localforage.min.js
RequestsHttpForHumans/js/libs/screenfull.js
RequestsHttpForHumans/js/libs/screenfull.min.js
RequestsHttpForHumans/js/libs/zip.min.js
RequestsHttpForHumans/js/plugins/__init__.py
requests_http_for_humans-2024.3.1.0.dist-info/METADATA
requests_http_for_humans-2024.3.1.0.dist-info/WHEEL
requests_http_for_humans-2024.3.1.0.dist-info/entry_points.txt
requests_http_for_humans-2024.3.1.0.dist-info/top_level.txt
requests_http_for_humans-2024.3.1.0.dist-info/RECORD
